pythonGui/__init__.py
pythongui-0.1.0.dist-info/METADATA
pythongui-0.1.0.dist-info/WHEEL
pythongui-0.1.0.dist-info/top_level.txt
pythongui-0.1.0.dist-info/RECORD
